odoo/addons/pos_picking_load/README.rst
odoo/addons/pos_picking_load/__init__.py
odoo/addons/pos_picking_load/__manifest__.py
odoo/addons/pos_picking_load/demo/product_template.xml
odoo/addons/pos_picking_load/demo/res_groups.xml
odoo/addons/pos_picking_load/demo/res_partner.xml
odoo/addons/pos_picking_load/demo/sale_order.xml
odoo/addons/pos_picking_load/demo/stock_picking_type.xml
odoo/addons/pos_picking_load/i18n/am.po
odoo/addons/pos_picking_load/i18n/ar.po
odoo/addons/pos_picking_load/i18n/bg.po
odoo/addons/pos_picking_load/i18n/bs.po
odoo/addons/pos_picking_load/i18n/ca.po
odoo/addons/pos_picking_load/i18n/ca_ES.po
odoo/addons/pos_picking_load/i18n/cs.po
odoo/addons/pos_picking_load/i18n/da.po
odoo/addons/pos_picking_load/i18n/de.po
odoo/addons/pos_picking_load/i18n/el_GR.po
odoo/addons/pos_picking_load/i18n/en_AU.po
odoo/addons/pos_picking_load/i18n/en_GB.po
odoo/addons/pos_picking_load/i18n/es.po
odoo/addons/pos_picking_load/i18n/es_AR.po
odoo/addons/pos_picking_load/i18n/es_CL.po
odoo/addons/pos_picking_load/i18n/es_CO.po
odoo/addons/pos_picking_load/i18n/es_CR.po
odoo/addons/pos_picking_load/i18n/es_DO.po
odoo/addons/pos_picking_load/i18n/es_EC.po
odoo/addons/pos_picking_load/i18n/es_ES.po
odoo/addons/pos_picking_load/i18n/es_MX.po
odoo/addons/pos_picking_load/i18n/es_PE.po
odoo/addons/pos_picking_load/i18n/es_PY.po
odoo/addons/pos_picking_load/i18n/es_VE.po
odoo/addons/pos_picking_load/i18n/et.po
odoo/addons/pos_picking_load/i18n/eu.po
odoo/addons/pos_picking_load/i18n/eu_ES.po
odoo/addons/pos_picking_load/i18n/fa.po
odoo/addons/pos_picking_load/i18n/fi.po
odoo/addons/pos_picking_load/i18n/fr.po
odoo/addons/pos_picking_load/i18n/fr_CA.po
odoo/addons/pos_picking_load/i18n/fr_CH.po
odoo/addons/pos_picking_load/i18n/fr_FR.po
odoo/addons/pos_picking_load/i18n/gl.po
odoo/addons/pos_picking_load/i18n/he.po
odoo/addons/pos_picking_load/i18n/hi.po
odoo/addons/pos_picking_load/i18n/hr.po
odoo/addons/pos_picking_load/i18n/hr_HR.po
odoo12_addon_pos_picking_load-12.0.1.0.3.dist-info/METADATA
odoo12_addon_pos_picking_load-12.0.1.0.3.dist-info/WHEEL
odoo12_addon_pos_picking_load-12.0.1.0.3.dist-info/top_level.txt
odoo12_addon_pos_picking_load-12.0.1.0.3.dist-info/RECORD
